setup.py
SquidUtils/__init__.py
SquidUtils.egg-info/PKG-INFO
SquidUtils.egg-info/SOURCES.txt
SquidUtils.egg-info/dependency_links.txt
SquidUtils.egg-info/not-zip-safe
SquidUtils.egg-info/top_level.txt
SquidUtils/db/__init__.py
SquidUtils/db/migrations.py