Metadata-Version: 1.0
Name: SquidUtils
Version: 0.1.1
Summary: Central server and controller for GiantSquid
Home-page: http://gitlab.com/GiantSquid/GiantSquid
Author: GiantSquid
Author-email: u@r0t.me
License: MIT
Platform: UNKNOWN
